{
    "listName": " 🧪🔬🌐🚀🧬 Decentralized Science and Biological Conservation Underrated Projects & Individuals",
    "listDescription": "In this unique curation, we spotlight the unsung heroes and underappreciated projects dedicated to advancing decentralized science and fostering biological conservation efforts. Within this curation, expect to delve into a treasure trove of pioneering projects that disrupt the traditional paradigms of scientific research and conservation. From grassroots movements employing decentralized technologies to facilitate open-access research, to the endeavors of individuals working quietly but profoundly to protect and preserve our planet's biodiversity, this curation sheds light on their impactful endeavors. This curated collection, endorsed by Greenpill México, emphasizes the urgent need to regenerate biological and complex systems within traditional science. Through innovative approaches and the exploration of new use cases, the initiative strives to revolutionize scientific practices toward a more decentralized and sustainable future. ",
    "impactEvaluationInput": "",
    "impactEvaluationDescription": "Created by greenpillmexico.town using RetroList with \"Categorization Only\" rubric.",
    "impactEvaluationLink": "https://retropgf3.retrolist.app/list/656d7c712a10f91def751c66",
    "impactEvaluationType": "rubric",
    "listContent": [
        {
            "RPGF3_Application_UID": "0x7abbdafaee87210e6340fa7d73be9d31fee4053e6543902e75bd3faf2d523cb1",
            "OPAmount": 0,
            "evaluation": {},
            "_id": "656d7c712a10f91def751c67"
        },
        {
            "RPGF3_Application_UID": "0xfd28d4d48ed3fa4b8986b814cda7a6535078967a7856cb9ab95742a95ae59974",
            "OPAmount": 0,
            "evaluation": {},
            "_id": "656d7c712a10f91def751c68"
        },
        {
            "RPGF3_Application_UID": "0x3f3be3996262f122877efc7d90672555eaf42a3d6cf6de7839a0282626aaa55f",
            "OPAmount": 0,
            "evaluation": {},
            "_id": "656d7c712a10f91def751c69"
        },
        {
            "RPGF3_Application_UID": "0x830b1298ed3f8504a0b04b1a7371257b9a98c165e73d6cb557d82fcb7d5f25cc",
            "OPAmount": 0,
            "evaluation": {},
            "_id": "656d7c712a10f91def751c6a"
        },
        {
            "RPGF3_Application_UID": "0x7f66e162c6ff0ebfc20fe8198af210936ff4917fc06c1c47630b89f3000958b4",
            "OPAmount": 0,
            "evaluation": {},
            "_id": "656d7c712a10f91def751c6b"
        },
        {
            "RPGF3_Application_UID": "0x8cce00b421d2f19c829d484b423a49f311d41355238c5c5a73b72d62c5c63f56",
            "OPAmount": 0,
            "evaluation": {},
            "_id": "656d7c712a10f91def751c6c"
        },
        {
            "RPGF3_Application_UID": "0x0044f3f713acfa58a80899a841e6f417f27c3f151d6302815944c89834a0db97",
            "OPAmount": 0,
            "evaluation": {},
            "_id": "656d7c712a10f91def751c6d"
        }
    ],
    "projectsMetadata": [
        {
            "id": "0x7abbdafaee87210e6340fa7d73be9d31fee4053e6543902e75bd3faf2d523cb1",
            "bio": "VitaDAO is a community owned collective funding early stage longevity research",
            "displayName": "VitaDAO",
            "profileImageUrl": null
        },
        {
            "id": "0xfd28d4d48ed3fa4b8986b814cda7a6535078967a7856cb9ab95742a95ae59974",
            "bio": "Director of Product at Molecule",
            "displayName": "Bio.xyz",
            "profileImageUrl": "https://content.optimism.io/profile/v0/profile-image/10/0xdF5D63B80D939Dedeb9C84B45B1D14A17c97802D.png"
        },
        {
            "id": "0x3f3be3996262f122877efc7d90672555eaf42a3d6cf6de7839a0282626aaa55f",
            "bio": "DeSci DAO Regenerating Coral Reef Conservation in Mesoamerica",
            "displayName": "MesoReefDAO",
            "profileImageUrl": "https://content.optimism.io/profile/v0/profile-image/10/0x156Bfd9395371F29489FaD5EDF29269b72908F68.png"
        },
        {
            "id": "0x830b1298ed3f8504a0b04b1a7371257b9a98c165e73d6cb557d82fcb7d5f25cc",
            "bio": "Join the movement towards a more sustainable and equitable future in #Medellín🌱",
            "displayName": "ReFi Medellín",
            "profileImageUrl": "https://content.optimism.io/profile/v0/profile-image/10/0x302E2A0D4291ac14Aa1160504cA45A0A1F2E7a5c.png"
        },
        {
            "id": "0x7f66e162c6ff0ebfc20fe8198af210936ff4917fc06c1c47630b89f3000958b4",
            "bio": "Advocating for regenerative economical approach | Onboarding and Edu events ",
            "displayName": "Refi Phangan",
            "profileImageUrl": "https://content.optimism.io/profile/v0/profile-image/10/0xa8258ED271BB9be9d7E16c5818E45eF6F2577d92.png"
        },
        {
            "id": "0x8cce00b421d2f19c829d484b423a49f311d41355238c5c5a73b72d62c5c63f56",
            "bio": "Reef scientist integrating public goods, DeSci, and web3, based in Latam Ü",
            "displayName": "Rodrigo NuñΞz",
            "profileImageUrl": "https://content.optimism.io/profile/v0/profile-image/10/0x4D5B28d08e8c00e041053b0dc584e00e6997Daa3.png"
        },
        {
            "id": "0x0044f3f713acfa58a80899a841e6f417f27c3f151d6302815944c89834a0db97",
            "bio": "Environmental scientists, blockchain & space enthusiast",
            "displayName": "Paul Burg",
            "profileImageUrl": "https://content.optimism.io/profile/v0/profile-image/10/0x50418699cB44BfDa9c9afc9B7a0b0d244d8927D2.png"
        }
    ],
    "status": "qualified",
    "walletAddress": "0x4D5B28d08e8c00e041053b0dc584e00e6997Daa3",
    "domainName": "greenpillmexico.town",
    "twitter": "GreenPillMexico",
    "discord": "rodotriton",
    "isBadgeholder": false,
    "attestationUid": "0x37213b48239bda9a9c6bf1c81b070a93dbf659360de385830f0a47633067037b",
    "approvalAttestationUid": null,
    "forkedFrom": null,
    "rubric": {
        "_id": "65695f889c41a3dbb680a30c",
        "createdBy": "Chomtana",
        "name": "Categorization Only",
        "__v": 0,
        "categories": [],
        "criteria": [
            {
                "title": "Categorization Only",
                "isNegative": false,
                "scores": {
                    "0": "Categorization Only"
                },
                "_id": "65695f88c417afa156a73138"
            }
        ],
        "description": "Categorization projects without allocating any OP to them",
        "isActive": true
    },
    "rubricId": "65695f889c41a3dbb680a30c",
    "categories": [],
    "histories": [],
    "createdAt": "2023-12-04T07:14:57.247Z",
    "updatedAt": "2023-12-04T07:15:36.668Z",
    "id": "656d7c712a10f91def751c66"
}